countrymapper/__init__.py
countrymapper/countrymapper.py
countrymapper-0.5.dist-info/METADATA
countrymapper-0.5.dist-info/WHEEL
countrymapper-0.5.dist-info/top_level.txt
countrymapper-0.5.dist-info/RECORD
