Metadata-Version: 2.1
Name: countrymapper
Version: 0.5
Summary: A simple tool to normalise/standardise country names to their official country names or codes
Author: Arfat Shaikh
